rectified_flows/__init__.py
rectified_flows/py.typed
rectified_flows/rectified_flows.py
rectified_flows-0.0.16.dist-info/METADATA
rectified_flows-0.0.16.dist-info/WHEEL
rectified_flows-0.0.16.dist-info/licenses/LICENSE
rectified_flows-0.0.16.dist-info/RECORD
