Metadata-Version: 2.4
Name: rectified-flows
Version: 0.0.16
Summary: Implementation of Rectified Flows in JAX and Equinox.
Author-email: homerjed <jedhmr@gmail.com>
License-File: LICENSE
Requires-Python: >=3.11
Requires-Dist: beartype>=0.21.0
Requires-Dist: cloudpickle>=3.1.1
Requires-Dist: diffrax>=0.7.0
Requires-Dist: einops>=0.8.1
Requires-Dist: einx>=0.3.0
Requires-Dist: equinox>=0.12.2
Requires-Dist: grain>=0.2.11
Requires-Dist: jax>=0.6.2
Requires-Dist: ml-collections>=1.1.0
Requires-Dist: numpy>=2.3.1
Requires-Dist: optax>=0.2.5
Requires-Dist: tqdm>=4.67.1
Provides-Extra: examples
Requires-Dist: datasets>=3.6.0; extra == 'examples'
Requires-Dist: matplotlib>=3.10.3; extra == 'examples'
Requires-Dist: pillow>=11.3.0; extra == 'examples'
